faz/utils/__init__.py
faz/utils/cache_util.py
faz/utils/retry_handler.py
faz/utils/database/__init__.py
faz/utils/database/base_database.py
faz/utils/database/base_model.py
faz/utils/database/base_mysql_database.py
faz/utils/database/base_repository.py
faz/utils/heartbeat/__init__.py
faz/utils/heartbeat/_heartbeat_task.py
faz/utils/heartbeat/base_heartbeat.py
faz/utils/heartbeat/task/__init__.py
faz/utils/heartbeat/task/itask.py
faz_utils-0.1.2.dist-info/LICENSE
faz_utils-0.1.2.dist-info/METADATA
faz_utils-0.1.2.dist-info/WHEEL
faz_utils-0.1.2.dist-info/top_level.txt
faz_utils-0.1.2.dist-info/RECORD
