Metadata-Version: 2.1
Name: faz-utils
Version: 0.1.2
Summary: Utility modules for faz projects
Author-email: FAZuH <fazuhhh@proton.me>
License: MIT License
Project-URL: Source, https://github.com/FAZuH/faz-utils
Project-URL: Issues, https://github.com/FAZuH/faz-utils/issues
Project-URL: Documentation, https://github.com/FAZuH/faz-utils#readme
Requires-Python: >=3.12
License-File: LICENSE
Requires-Dist: loguru>=0.7.2
Requires-Dist: sqlalchemy>=2.0.36
